azure/mgmt/testbase/__init__.py
azure/mgmt/testbase/_configuration.py
azure/mgmt/testbase/_patch.py
azure/mgmt/testbase/_serialization.py
azure/mgmt/testbase/_test_base.py
azure/mgmt/testbase/_vendor.py
azure/mgmt/testbase/_version.py
azure/mgmt/testbase/py.typed
azure/mgmt/testbase/aio/__init__.py
azure/mgmt/testbase/aio/_configuration.py
azure/mgmt/testbase/aio/_patch.py
azure/mgmt/testbase/aio/_test_base.py
azure/mgmt/testbase/aio/operations/__init__.py
azure/mgmt/testbase/aio/operations/_analysis_results_operations.py
azure/mgmt/testbase/aio/operations/_available_os_operations.py
azure/mgmt/testbase/aio/operations/_billing_hub_service_operations.py
azure/mgmt/testbase/aio/operations/_customer_events_operations.py
azure/mgmt/testbase/aio/operations/_email_events_operations.py
azure/mgmt/testbase/aio/operations/_favorite_processes_operations.py
azure/mgmt/testbase/aio/operations/_flighting_rings_operations.py
azure/mgmt/testbase/aio/operations/_operations.py
azure/mgmt/testbase/aio/operations/_os_updates_operations.py
azure/mgmt/testbase/aio/operations/_packages_operations.py
azure/mgmt/testbase/aio/operations/_patch.py
azure/mgmt/testbase/aio/operations/_skus_operations.py
azure/mgmt/testbase/aio/operations/_test_base_accounts_operations.py
azure/mgmt/testbase/aio/operations/_test_results_operations.py
azure/mgmt/testbase/aio/operations/_test_summaries_operations.py
azure/mgmt/testbase/aio/operations/_test_types_operations.py
azure/mgmt/testbase/aio/operations/_usage_operations.py
azure/mgmt/testbase/models/__init__.py
azure/mgmt/testbase/models/_models_py3.py
azure/mgmt/testbase/models/_patch.py
azure/mgmt/testbase/models/_test_base_enums.py
azure/mgmt/testbase/operations/__init__.py
azure/mgmt/testbase/operations/_analysis_results_operations.py
azure/mgmt/testbase/operations/_available_os_operations.py
azure/mgmt/testbase/operations/_billing_hub_service_operations.py
azure/mgmt/testbase/operations/_customer_events_operations.py
azure_mgmt_testbase-1.0.0b2.dist-info/LICENSE
azure_mgmt_testbase-1.0.0b2.dist-info/METADATA
azure_mgmt_testbase-1.0.0b2.dist-info/WHEEL
azure_mgmt_testbase-1.0.0b2.dist-info/top_level.txt
azure_mgmt_testbase-1.0.0b2.dist-info/RECORD
